decryptomatte/__init__.py
decryptomatte/decrpyt_utils.py
decryptomatte/decrypt.py
decryptomatte/open_image_util.py
decryptomatte/utils.py
decryptomatte-1.0.1.dist-info/LICENSE
decryptomatte-1.0.1.dist-info/METADATA
decryptomatte-1.0.1.dist-info/WHEEL
decryptomatte-1.0.1.dist-info/RECORD
