Metadata-Version: 2.1
Name: decryptomatte
Version: 1.0.1
Summary: Extract Cryptomatte data from EXR image files
Home-page: https://github.com/tappi287/decryptomatte
License: MIT
Author: tappi287
Author-email: tapper.stefan@gmail.com
Requires-Python: >=3.9,<3.12
Classifier: License :: OSI Approved :: MIT License
Classifier: Programming Language :: Python :: 3
Classifier: Programming Language :: Python :: 3.9
Classifier: Programming Language :: Python :: 3.10
Classifier: Programming Language :: Python :: 3.11
Requires-Dist: mmh3
Requires-Dist: numpy (>=1.26.4,<2.0.0)
Requires-Dist: openimageio (>=2.0.7,<3.0.0) ; python_version == "3.10"
Requires-Dist: openimageio (>=2.5.8.0,<3.0.0.0) ; python_version == "3.11"
Project-URL: Repository, https://github.com/tappi287/decryptomatte
